setup.cfg
setup.py
docker_rmi/__init__.py
docker_rmi/cli.py
docker_rmi.egg-info/PKG-INFO
docker_rmi.egg-info/SOURCES.txt
docker_rmi.egg-info/dependency_links.txt
docker_rmi.egg-info/entry_points.txt
docker_rmi.egg-info/not-zip-safe
docker_rmi.egg-info/requires.txt
docker_rmi.egg-info/top_level.txt