Metadata-Version: 1.1
Name: docker-rmi
Version: 1.0.1
Summary: README.md
Home-page: https://github.com/vankhoa011/docker-remove-images
Author: Nguyen Vu Van Khoa
Author-email: vankhoa011@gmail.com
License: BSD
Platform: linux
Classifier: Development Status :: 5 - Production/Stable
Classifier: Environment :: Console
Classifier: Intended Audience :: Developers
Classifier: License :: OSI Approved :: BSD License
Classifier: Operating System :: Unix
Classifier: Programming Language :: Python
Classifier: Programming Language :: Python :: 2
Classifier: Topic :: Software Development :: Libraries :: Python Modules
